crm_automator-1.11.5.dist-info/licenses/LICENSE
eml/__init__.py
eml/crm_client.py
eml/eml_automator.py
eml/intelligence.py
eml/migrate_jsonl_to_sqlite.py
eml/persistence.py
eml/web_ui.py
eml/docs/agent_demo.py
eml/filters/__init__.py
eml/filters/categories.py
eml/filters/content_cleaner.py
eml/filters/eesa_filter.py
eml/filters/heuristic_filter.py
eml/filters/llm_classifier.py
eml/filters/llm_config.py
eml/filters/llm_error_handler.py
eml/filters/logging.py
eml/filters/orchestrator.py
eml/web/__init__.py
eml/web/analytics.py
eml/web/components.py
eml/web/config.py
eml/web/state.py
eml/web/tabs/__init__.py
eml/web/views/__init__.py
eml/web/views/detail_modal.py
crm_automator-1.11.5.dist-info/METADATA
crm_automator-1.11.5.dist-info/WHEEL
crm_automator-1.11.5.dist-info/entry_points.txt
crm_automator-1.11.5.dist-info/top_level.txt
crm_automator-1.11.5.dist-info/RECORD
