Metadata-Version: 2.4
Name: crm-automator
Version: 1.11.5
Summary: AI-powered email processing and CRM automation
Requires-Python: >=3.10
License-File: LICENSE
Requires-Dist: openai>=1.0.0
Requires-Dist: instructor
Requires-Dist: python-dotenv
Requires-Dist: requests
Requires-Dist: beautifulsoup4
Requires-Dist: email-reply-parser
Requires-Dist: markdownify
Requires-Dist: ddgs
Requires-Dist: crawl4ai>=0.7.0
Requires-Dist: tqdm
Requires-Dist: nicegui>=3.4.1
Provides-Extra: dev
Requires-Dist: pytest; extra == "dev"
Requires-Dist: black; extra == "dev"
Requires-Dist: ruff; extra == "dev"
Dynamic: license-file
